Metadata-Version: 2.0
Name: helga-youtube-meta
Version: 1.1.0
Summary: Provide information for youtube related metadata
Home-page: https://github.com/narfman0/helga-youtube-metadata
Author: Jon Robison
Author-email: narfman0@gmail.com
License: LICENSE
Keywords: irc bot youtube-meta
Platform: UNKNOWN
Classifier: Development Status :: 4 - Beta
Classifier: Topic :: Communications :: Chat :: Internet Relay Chat
Classifier: License :: OSI Approved :: GNU General Public License v3 (GPLv3)
Classifier: Operating System :: OS Independent
Classifier: Programming Language :: Python
Classifier: Topic :: Software Development :: Libraries :: Python Modules
Classifier: Topic :: Communications :: Chat :: Internet Relay Chat
Requires-Dist: helga
Requires-Dist: python-dateutil
Requires-Dist: requests
